pc_metrics/__init__.py
pc_metrics/metrics.py
pc_metrics/utils/__cd__.py
pc_metrics/utils/__emd__.py
pc_metrics/utils/__init__.py
pc_metrics-0.2.5.dist-info/METADATA
pc_metrics-0.2.5.dist-info/WHEEL
pc_metrics-0.2.5.dist-info/top_level.txt
pc_metrics-0.2.5.dist-info/RECORD
