Metadata-Version: 2.4
Name: pc_metrics
Version: 0.2.5
Summary: Point Cloud Evaluation Metrics
Home-page: https://github.com/URRealHero/point_cloud_metrics
Author: Shu Pu
Author-email: pushuabc@gmail.com
Classifier: Programming Language :: Python :: 3
Classifier: License :: OSI Approved :: MIT License
Classifier: Operating System :: OS Independent
Requires-Python: >=3.8
Requires-Dist: numpy>=1.20
Requires-Dist: scipy>=1.7
Requires-Dist: scikit-learn>=1.0
Dynamic: author
Dynamic: author-email
Dynamic: classifier
Dynamic: description
Dynamic: description-content-type
Dynamic: home-page
Dynamic: requires-dist
Dynamic: requires-python
Dynamic: summary
